Workbook
Name Slicer_Department: #N/A
Name Slicer_Month: #N/A

Sheet Dashboard
AF2: =IFERROR(GETPIVOTDATA("Sum of Amount (INR)",Pivot!$M$3),0) -> 18405183
AF3: =IFERROR(GETPIVOTDATA("Sum of Budget Allocated",Pivot!$M$3),0) -> 22953950
AF4: =IFERROR(GETPIVOTDATA("Sum of Budget Remaining",Pivot!$M$3),0) -> 4548767
AF5: =IFERROR(GETPIVOTDATA("Count of Expense ID",Pivot!$M$3),0) -> 415
AF6: =IFERROR(GETPIVOTDATA("Count of Expense ID",Pivot!$J$3,"Approved","Yes")/AF5,0) -> 0.81445783
AF7: =IFERROR(AF2/AF5,0) -> 44349.839

Sheet Data
A1: Expense ID | B1: Date | C1: Department | D1: Category | E1: Amount (INR) | F1: Payment Method | G1: Approved | H1: Budget Allocated | I1: Budget Remaining | J1: Month
A2: EXP-5001 | B2: 45682 | C2: Engineering | D2: Software | E2: 7099 | F2: Cash | G2: Yes | H2: 8386 | I2: 1287 | J2: =TEXT(tblExpenses[[#This Row],[Date]],"mmm") -> Jan
A3: EXP-5002 | B3: 45677 | C3: Engineering | D3: Marketing | E3: 37909 | F3: Credit Card | G3: Yes | H3: 39147 | I3: 1238 | J3: =TEXT(tblExpenses[[#This Row],[Date]],"mmm") -> Jan
A4: EXP-5003 | B4: 45665 | C4: Engineering | D4: Office Supplies | E4: 5729 | F4: Cash | G4: Yes | H4: 8391 | I4: 2662 | J4: =TEXT(tblExpenses[[#This Row],[Date]],"mmm") -> Jan
A5: EXP-5004 | B5: 45660 | C5: Marketing | D5: Consulting | E5: 21974 | F5: Cash | G5: Yes | H5: 22502 | I5: 528 | J5: =TEXT(tblExpenses[[#This Row],[Date]],"mmm") -> Jan
A6: EXP-5005 | B6: 45682 | C6: Marketing | D6: Equipment | E6: 70564 | F6: Cheque | G6: Yes | H6: 77440 | I6: 6876 | J6: =TEXT(tblExpenses[[#This Row],[Date]],"mmm") -> Jan
A7: EXP-5006 | B7: 45681 | C7: Marketing | D7: Software | E7: 23713 | F7: Credit Card | G7: No | H7: 28542 | I7: 4829 | J7: =TEXT(tblExpenses[[#This Row],[Date]],"mmm") -> Jan
A8: EXP-5007 | B8: 45685 | C8: Sales | D8: Equipment | E8: 67515 | F8: Credit Card | G8: Yes | H8: 87309 | I8: 19794 | J8: =TEXT(tblExpenses[[#This Row],[Date]],"mmm") -> Jan
A9: EXP-5008 | B9: 45660 | C9: Sales | D9: Consulting | E9: 30644 | F9: Bank Transfer | G9: Yes | H9: 44207 | I9: 13563 | J9: =TEXT(tblExpenses[[#This Row],[Date]],"mmm") -> Jan
A10: EXP-5009 | B10: 45668 | C10: Sales | D10: Utilities | E10: 8331 | F10: Cash | G10: Yes | H10: 11602 | I10: 3271 | J10: =TEXT(tblExpenses[[#This Row],[Date]],"mmm") -> Jan
A11: EXP-5010 | B11: 45677 | C11: Sales | D11: Travel | E11: 55807 | F11: Credit Card | G11: Yes | H11: 62479 | I11: 6672 | J11: =TEXT(tblExpenses[[#This Row],[Date]],"mmm") -> Jan
A12: EXP-5011 | B12: 45662 | C12: Sales | D12: Consulting | E12: 35534 | F12: Cash | G12: No | H12: 49832 | I12: 14298 | J12: =TEXT(tblExpenses[[#This Row],[Date]],"mmm") -> Jan
A13: EXP-5012 | B13: 45667 | C13: Sales | D13: Software | E13: 31806 | F13: Bank Transfer | G13: Yes | H13: 36795 | I13: 4989 | J13: =TEXT(tblExpenses[[#This Row],[Date]],"mmm") -> Jan
... A416: EXP-5415 | B416: 46019 | C416: Operations | D416: Software | E416: 26583 | F416: Bank Transfer | G416: Yes | H416: 26921 | I416: 338 | J416: =TEXT(tblExpenses[[#This Row],[Date]],"mmm") -> Dec

Sheet Pivot
A3: Department | B3: Sum of Amount (INR) | D3: Category | E3: Sum of Amount (INR) | G3: Month | H3: Sum of Amount (INR) | J3: Approved | K3: Sum of Amount (INR) | L3: Count of Expense ID | M3: Sum of Amount (INR) | N3: Sum of Budget Allocated | O3: Sum of Budget Remaining | P3: Count of Expense ID
A4: Engineering | B4: 3366315 | D4: Consulting | E4: 6030171 | G4: Jan | H4: 1379978 | J4: No | K4: 3628179 | L4: 77 | M4: 18405183 | N4: 22953950 | O4: 4548767 | P4: 415
A5: Finance | B5: 2611075 | D5: Equipment | E5: 3671418 | G5: Feb | H5: 1058599 | J5: Yes | K5: 14777004 | L5: 338
A6: HR | B6: 3616924 | D6: Marketing | E6: 3505155 | G6: Mar | H6: 1179601 | J6: Grand Total | K6: 18405183 | L6: 415
A7: Marketing | B7: 3010276 | D7: Office Supplies | E7: 208093 | G7: Apr | H7: 1317668
A8: Operations | B8: 3346621 | D8: Software | E8: 1743238 | G8: May | H8: 1780658
A9: Sales | B9: 2453972 | D9: Training | E9: 772840 | G9: Jun | H9: 1286080
A10: Grand Total | B10: 18405183 | D10: Travel | E10: 2023948 | G10: Jul | H10: 2119404
D11: Utilities | E11: 450320 | G11: Aug | H11: 1669539
D12: Grand Total | E12: 18405183 | G12: Sep | H12: 1913484
G13: Oct | H13: 1365637
G14: Nov | H14: 1795988
G15: Dec | H15: 1538547
G16: Grand Total | H16: 18405183
A25: Payment Method | B25: Sum of Amount (INR) | D25: Department | E25: Actual Spent | F25: Sum of Budget Allocated
A26: Bank Transfer | B26: 4908988 | D26: Engineering | E26: 3366315 | F26: 4162201
A27: Cash | B27: 4388835 | D27: Finance | E27: 2611075 | F27: 3159110
A28: Cheque | B28: 5477461 | D28: HR | E28: 3616924 | F28: 4425089
A29: Credit Card | B29: 3629899 | D29: Marketing | E29: 3010276 | F29: 3898633
A30: Grand Total | B30: 18405183 | D30: Operations | E30: 3346621 | F30: 4160632
D31: Sales | E31: 2453972 | F31: 3148285
D32: Grand Total | E32: 18405183 | F32: 22953950
A50: Department | B50: Amount | D50: Category | E50: Amount | G50: Month | H50: Amount | J50: Payment Method | K50: Amount | M50: Department | N50: Actual Spent | O50: Budget Allocated
A51: =Pivot!$A$4 -> Engineering | B51: =Pivot!$B$4 -> 3366315 | D51: =Pivot!$D$4 -> Consulting | E51: =Pivot!$E$4 -> 6030171 | G51: =Pivot!$G$4 -> Jan | H51: =Pivot!$H$4 -> 1379978 | J51: =Pivot!$A$26 -> Bank Transfer | K51: =Pivot!$B$26 -> 4908988 | M51: =Pivot!$D$26 -> Engineering | N51: =Pivot!$E$26 -> 3366315 | O51: =Pivot!$F$26 -> 4162201
A52: =Pivot!$A$5 -> Finance | B52: =Pivot!$B$5 -> 2611075 | D52: =Pivot!$D$5 -> Equipment | E52: =Pivot!$E$5 -> 3671418 | G52: =Pivot!$G$5 -> Feb | H52: =Pivot!$H$5 -> 1058599 | J52: =Pivot!$A$27 -> Cash | K52: =Pivot!$B$27 -> 4388835 | M52: =Pivot!$D$27 -> Finance | N52: =Pivot!$E$27 -> 2611075 | O52: =Pivot!$F$27 -> 3159110
A53: =Pivot!$A$6 -> HR | B53: =Pivot!$B$6 -> 3616924 | D53: =Pivot!$D$6 -> Marketing | E53: =Pivot!$E$6 -> 3505155 | G53: =Pivot!$G$6 -> Mar | H53: =Pivot!$H$6 -> 1179601 | J53: =Pivot!$A$28 -> Cheque | K53: =Pivot!$B$28 -> 5477461 | M53: =Pivot!$D$28 -> HR | N53: =Pivot!$E$28 -> 3616924 | O53: =Pivot!$F$28 -> 4425089
A54: =Pivot!$A$7 -> Marketing | B54: =Pivot!$B$7 -> 3010276 | D54: =Pivot!$D$7 -> Office Supplies | E54: =Pivot!$E$7 -> 208093 | G54: =Pivot!$G$7 -> Apr | H54: =Pivot!$H$7 -> 1317668 | J54: =Pivot!$A$29 -> Credit Card | K54: =Pivot!$B$29 -> 3629899 | M54: =Pivot!$D$29 -> Marketing | N54: =Pivot!$E$29 -> 3010276 | O54: =Pivot!$F$29 -> 3898633
A55: =Pivot!$A$8 -> Operations | B55: =Pivot!$B$8 -> 3346621 | D55: =Pivot!$D$8 -> Software | E55: =Pivot!$E$8 -> 1743238 | G55: =Pivot!$G$8 -> May | H55: =Pivot!$H$8 -> 1780658 | M55: =Pivot!$D$30 -> Operations | N55: =Pivot!$E$30 -> 3346621 | O55: =Pivot!$F$30 -> 4160632
A56: =Pivot!$A$9 -> Sales | B56: =Pivot!$B$9 -> 2453972 | D56: =Pivot!$D$9 -> Training | E56: =Pivot!$E$9 -> 772840 | G56: =Pivot!$G$9 -> Jun | H56: =Pivot!$H$9 -> 1286080 | M56: =Pivot!$D$31 -> Sales | N56: =Pivot!$E$31 -> 2453972 | O56: =Pivot!$F$31 -> 3148285
D57: =Pivot!$D$10 -> Travel | E57: =Pivot!$E$10 -> 2023948 | G57: =Pivot!$G$10 -> Jul | H57: =Pivot!$H$10 -> 2119404
D58: =Pivot!$D$11 -> Utilities | E58: =Pivot!$E$11 -> 450320 | G58: =Pivot!$G$11 -> Aug | H58: =Pivot!$H$11 -> 1669539
G59: =Pivot!$G$12 -> Sep | H59: =Pivot!$H$12 -> 1913484
G60: =Pivot!$G$13 -> Oct | H60: =Pivot!$H$13 -> 1365637
G61: =Pivot!$G$14 -> Nov | H61: =Pivot!$H$14 -> 1795988
G62: =Pivot!$G$15 -> Dec | H62: =Pivot!$H$15 -> 1538547
